{
  "main": {
    "id": "29f9f16e6b7aa78d",
    "type": "split",
    "children": [
      {
        "id": "3692ddd1a8b6439f",
        "type": "tabs",
        "children": [
          {
            "id": "3d381c783d3c1a4e",
            "type": "leaf",
            "state": {
              "type": "markdown",
              "state": {
                "file": "Estrutura/Etapa 1.md",
                "mode": "source",
                "source": false
              }
            }
          }
        ]
      }
    ],
    "direction": "vertical"
  },
  "left": {
    "id": "6a3ddf425e350375",
    "type": "split",
    "children": [
      {
        "id": "e21819f72606efe1",
        "type": "tabs",
        "children": [
          {
            "id": "32a521d707f6c812",
            "type": "leaf",
            "state": {
              "type": "file-explorer",
              "state": {
                "sortOrder": "alphabetical"
              }
            }
          },
          {
            "id": "1a4b119bfe89f1a3",
            "type": "leaf",
            "state": {
              "type": "search",
              "state": {
                "query": "",
                "matchingCase": false,
                "explainSearch": false,
                "collapseAll": false,
                "extraContext": false,
                "sortOrder": "alphabetical"
              }
            }
          },
          {
            "id": "50a4da97be421f08",
            "type": "leaf",
            "state": {
              "type": "bookmarks",
              "state": {}
            }
          },
          {
            "id": "275881fdf16634c9",
            "type": "leaf",
            "state": {
              "type": "mk-path-view",
              "state": {}
            }
          }
        ],
        "currentTab": 3
      }
    ],
    "direction": "horizontal",
    "width": 300
  },
  "right": {
    "id": "ca2dbb2848b5a3ce",
    "type": "split",
    "children": [
      {
        "id": "3f298bd04d2dc848",
        "type": "tabs",
        "children": [
          {
            "id": "9ee350ba99f64804",
            "type": "leaf",
            "state": {
              "type": "backlink",
              "state": {
                "file": "Estrutura/Etapa 1.md",
                "collapseAll": false,
                "extraContext": false,
                "sortOrder": "alphabetical",
                "showSearch": false,
                "searchQuery": "",
                "backlinkCollapsed": false,
                "unlinkedCollapsed": true
              }
            }
          },
          {
            "id": "a9052ff3939a489f",
            "type": "leaf",
            "state": {
              "type": "outgoing-link",
              "state": {
                "file": "Estrutura/Etapa 1.md",
                "linksCollapsed": false,
                "unlinkedCollapsed": true
              }
            }
          },
          {
            "id": "36cbdb0ae59fc7aa",
            "type": "leaf",
            "state": {
              "type": "tag",
              "state": {
                "sortOrder": "frequency",
                "useHierarchy": true
              }
            }
          },
          {
            "id": "3767e5d12780679e",
            "type": "leaf",
            "state": {
              "type": "outline",
              "state": {
                "file": "Estrutura/Etapa 1.md"
              }
            }
          }
        ],
        "currentTab": 3
      }
    ],
    "direction": "horizontal",
    "width": 300,
    "collapsed": true
  },
  "left-ribbon": {
    "hiddenItems": {
      "switcher:Abrir a troca rápida": false,
      "graph:Abrir visualização em gráfico": false,
      "canvas:Criar novo canvas": false,
      "daily-notes:Abrir a nota de hoje": false,
      "templates:Inserir modelo": false,
      "command-palette:Abrir paleta de comandos": false
    }
  },
  "active": "3d381c783d3c1a4e",
  "lastOpenFiles": [
    "Quadro/Contexto geral.canvas",
    "Estrutura/Etapa 1.md",
    "Tags",
    "Personagens/Secundários/Comunidade/Velho doido.md",
    "Personagens/Secundários/Comunidade/Eloá.md",
    "Personagens/Secundários/Comunidade/Velho doido (Barba Ruiva).md",
    "Personagens/Secundários/Comunidade/Catarina.md",
    "Ideias/Estrutura/Estrutura - ideia 4.md",
    "Personagens/Principais/Menina.md",
    "Imagens/Menina/Menina.md",
    "Imagens/EstruturaDeMapas.drawio.svg",
    "Personagens/Secundários/Floresta/Animais/Normais/Guaxinim.md",
    "Personagens/Secundários/Floresta/Animais/Normais/Boto.md",
    "Personagens/Secundários/Floresta/Animais/Corrompidos/Anta corrompida.md",
    "Ideias/Estrutura/Estrutura - ideia 1.md",
    "Personagens/Principais/Curupira.md",
    "Personagens/Principais/Saci Pererê.md",
    "Personagens/Principais/Matinta Perera.md",
    "Personagens/Principais/Iara.md",
    "Imagens/Matinta/Matinta - referência 12.png",
    "Imagens/Matinta/Matinta - referência 2.png",
    "Ideias/Estrutura/Estrutura - ideia 2.md",
    "Personagens/Secundários/Floresta/Animais/Normais/Ariranha.md",
    "Personagens/Secundários/Floresta/Animais/Corrompidos/Ariranha corrompida.md",
    "Personagens/Secundários/Floresta/Animais/Normais/Untitled 1.md",
    "Personagens/Secundários/Comunidade/Seu Pedro.md",
    "Personagens/Secundários/Comunidade/Velha Nâmia.md",
    "Personagens/Secundários/Comunidade/Pedrinho.md",
    "Personagens/Secundários/Comunidade/Seu João.md",
    "Personagens/Secundários/Comunidade/Ladrão.md",
    "Ideias/Estrutura",
    "Imagens/Cuca/Cuca - referência 1.png",
    "Imagens/Curupira/Curupira - referência 1.png",
    "Imagens/Cuca",
    "Imagens/Cuca/Cuca - referência 5.png",
    "Imagens/Cuca/Cuca - referência 10.png",
    "Imagens/Cuca/Cuca - referência 9.png",
    "Imagens/Cuca/Cuca - referência 8.png",
    "Imagens/Cuca/Cuca - referência 7.png",
    "Imagens/Curupira",
    "Imagens/Matinta",
    "Imagens/Menina",
    "Quadro",
    "Personagens/Principais/Untitled.canvas",
    "Imagens",
    "Nova pasta",
    "Personagens/Secundários/Floresta/Animais/Corrompidos"
  ]
}